paypal_payments_sdk-1.1.0.dist-info/licenses/LICENSE
paypal_sdk/__init__.py
paypal_sdk/client.py
paypal_sdk/exceptions.py
paypal_sdk/models.py
tests/__init__.py
tests/test_client.py
tests/test_transaction_search.py
paypal_payments_sdk-1.1.0.dist-info/METADATA
paypal_payments_sdk-1.1.0.dist-info/WHEEL
paypal_payments_sdk-1.1.0.dist-info/top_level.txt
paypal_payments_sdk-1.1.0.dist-info/RECORD
